{"skeleton":{"hash":"yBfdBZGyJi4","spine":"4.2.37","x":-960,"y":-540,"width":1920,"height":1080,"images":"./Sprite/Egypt_transition/","audio":""},"bones":[{"name":"root","color":"ff0000ff","icon":"warning"},{"name":"Main","parent":"root","color":"ffe500ff","icon":"square"},{"name":"transition","parent":"Main","scaleX":4,"scaleY":4,"color":"9b00ffff","icon":"particles"}],"slots":[{"name":"Egypt_transition-Egypt_transition_1","bone":"transition","attachment":"Egypt_transition/Egypt_transition_"}],"skins":[{"name":"default","attachments":{"Egypt_transition-Egypt_transition_1":{"Egypt_transition/Egypt_transition_":{"type":"mesh","uvs":[1,1,0,1,0,0,1,0],"triangles":[1,2,3,1,3,0],"vertices":[240,-135,-240,-135,-240,135,240,135],"hull":4,"sequence":{"count":30},"edges":[0,2,2,4,4,6,0,6],"width":480,"height":270}}}}],"animations":{"Symbol_animation":{"bones":{"root":{"scale":[{"time":1}]}},"attachments":{"default":{"Egypt_transition-Egypt_transition_1":{"Egypt_transition/Egypt_transition_":{"sequence":[{"mode":"loop","delay":0.0333}]}}}}}}}